gitsshkey/__init__.py
gitsshkey/main.py
git_ssh_key-0.1.5.dist-info/entry_points.txt
git_ssh_key-0.1.5.dist-info/WHEEL
git_ssh_key-0.1.5.dist-info/METADATA
git_ssh_key-0.1.5.dist-info/license_files/LICENSE
git_ssh_key-0.1.5.dist-info/RECORD
