Metadata-Version: 2.1
Name: git-ssh-key
Version: 0.1.5
Summary: UNKNOWN
License: MIT
Author-email: alingse <alingse@foxmail.com>
Requires-Python: >=3.6
Requires-Dist: click>=7
Requires-Dist: giturlparse>=0.10.0
Requires-Dist: sshconf>=0.2.4
Project-URL: homepage, https://github.com/alingse/git-ssh-key
